vibe/__init__.py
vibe/acp/__init__.py
vibe/acp/acp_agent.py
vibe/acp/entrypoint.py
vibe/acp/utils.py
vibe/acp/tools/__init__.py
vibe/acp/tools/base.py
vibe/acp/tools/session_update.py
vibe/acp/tools/builtins/bash.py
vibe/acp/tools/builtins/read_file.py
vibe/acp/tools/builtins/search_replace.py
vibe/acp/tools/builtins/todo.py
vibe/acp/tools/builtins/write_file.py
vibe/cli/__init__.py
vibe/cli/clipboard.py
vibe/cli/commands.py
vibe/cli/entrypoint.py
vibe/cli/history_manager.py
vibe/cli/autocompletion/__init__.py
vibe/cli/autocompletion/base.py
vibe/cli/autocompletion/path_completion.py
vibe/cli/autocompletion/slash_command.py
vibe/cli/textual_ui/__init__.py
vibe/cli/textual_ui/app.py
vibe/cli/textual_ui/app.tcss
vibe/cli/textual_ui/handlers/__init__.py
vibe/cli/textual_ui/handlers/event_handler.py
vibe/cli/textual_ui/renderers/__init__.py
vibe/cli/textual_ui/renderers/tool_renderers.py
vibe/cli/textual_ui/widgets/__init__.py
vibe/cli/textual_ui/widgets/approval_app.py
vibe/cli/textual_ui/widgets/blinking_message.py
vibe/cli/textual_ui/widgets/compact.py
vibe/cli/textual_ui/widgets/config_app.py
vibe/cli/textual_ui/widgets/context_progress.py
vibe/cli/textual_ui/widgets/loading.py
vibe/cli/textual_ui/widgets/messages.py
vibe/cli/textual_ui/widgets/mode_indicator.py
vibe/cli/textual_ui/widgets/path_display.py
vibe/cli/textual_ui/widgets/tool_widgets.py
vibe/cli/textual_ui/widgets/tools.py
vibe/cli/textual_ui/widgets/welcome.py
vibe/cli/textual_ui/widgets/chat_input/__init__.py
vibe/cli/textual_ui/widgets/chat_input/body.py
vibe/cli/textual_ui/widgets/chat_input/completion_manager.py
vibe/cli/textual_ui/widgets/chat_input/completion_popup.py
vibe/cli/textual_ui/widgets/chat_input/container.py
vibe/cli/textual_ui/widgets/chat_input/text_area.py
vibe/cli/update_notifier/__init__.py
vibe/cli/update_notifier/version_update.py
vibe/cli/update_notifier/adapters/filesystem_update_cache_repository.py
vibe/cli/update_notifier/adapters/github_version_update_gateway.py
ccvibe-1.1.4.dist-info/METADATA
ccvibe-1.1.4.dist-info/WHEEL
ccvibe-1.1.4.dist-info/entry_points.txt
ccvibe-1.1.4.dist-info/licenses/LICENSE
ccvibe-1.1.4.dist-info/RECORD
