Metadata-Version: 2.4
Name: ccvibe
Version: 1.1.4
Summary: Open source CLI coding agent powered by Claude
Project-URL: Homepage, https://github.com/mistralai/mistral-vibe
Project-URL: Repository, https://github.com/mistralai/mistral-vibe
Project-URL: Issues, https://github.com/mistralai/mistral-vibe/issues
Project-URL: Documentation, https://github.com/mistralai/mistral-vibe#readme
Author: Claude Vibe Contributors
License: Apache-2.0
License-File: LICENSE
Keywords: ai,anthropic,claude,cli,coding-assistant,developer-tools,llm
Classifier: Development Status :: 5 - Production/Stable
Classifier: Intended Audience :: Developers
Classifier: License :: OSI Approved :: Apache Software License
Classifier: Operating System :: OS Independent
Classifier: Programming Language :: Python
Classifier: Programming Language :: Python :: 3
Classifier: Programming Language :: Python :: 3.12
Classifier: Topic :: Software Development
Classifier: Topic :: Software Development :: Libraries :: Python Modules
Classifier: Topic :: Utilities
Requires-Python: >=3.12
Requires-Dist: agent-client-protocol==0.6.3
Requires-Dist: aiofiles>=24.1.0
Requires-Dist: anthropic>=0.75.0
Requires-Dist: httpx>=0.28.1
Requires-Dist: loguru>=0.7.3
Requires-Dist: mcp>=1.14.0
Requires-Dist: mistralai==1.9.11
Requires-Dist: openai>=2.13.0
Requires-Dist: packaging>=24.1
Requires-Dist: pexpect>=4.9.0
Requires-Dist: pydantic-settings>=2.12.0
Requires-Dist: pydantic>=2.12.4
Requires-Dist: pyperclip>=1.11.0
Requires-Dist: python-dotenv>=1.0.0
Requires-Dist: rich>=14.0.0
Requires-Dist: textual-speedups>=0.2.1
Requires-Dist: textual>=1.0.0
Requires-Dist: tomli-w>=1.2.0
Requires-Dist: watchfiles>=1.1.1
